py_uds-3.1.1.dist-info/licenses/LICENSE
uds/__init__.py
uds/__init__.pyi
uds/client.py
uds/addressing/__init__.py
uds/addressing/abstract_addressing_information.py
uds/addressing/addressing_type.py
uds/addressing/transmission_direction.py
uds/can/__init__.py
uds/can/frame.py
uds/can/segmenter.py
uds/can/addressing/__init__.py
uds/can/addressing/abstract_addressing_information.py
uds/can/addressing/addressing_format.py
uds/can/addressing/addressing_information.py
uds/can/addressing/extended_addressing.py
uds/can/addressing/mixed_addressing.py
uds/can/addressing/normal_addressing.py
uds/can/packet/__init__.py
uds/can/packet/abstract_container.py
uds/can/packet/can_packet.py
uds/can/packet/can_packet_record.py
uds/can/packet/can_packet_type.py
uds/can/packet/consecutive_frame.py
uds/can/packet/first_frame.py
uds/can/packet/flow_control.py
uds/can/packet/single_frame.py
uds/can/transport_interface/__init__.py
uds/can/transport_interface/common.py
uds/can/transport_interface/python_can.py
uds/message/__init__.py
uds/message/nrc.py
uds/message/service_identifiers.py
uds/message/uds_message.py
uds/packet/__init__.py
uds/packet/abstract_packet.py
uds/packet/abstract_packet_type.py
uds/segmentation/__init__.py
uds/segmentation/abstract_segmenter.py
uds/translator/__init__.py
uds/translator/service.py
uds/translator/translator.py
uds/translator/translator_definitions.py
uds/translator/data_record/__init__.py
uds/translator/data_record/abstract_data_record.py
uds/translator/data_record/conditional_data_record.py
uds/translator/data_record/formula_data_record.py
uds/translator/data_record/mapping_data_record.py
uds/translator/data_record/raw_data_record.py
uds/translator/data_record/text_data_record.py
uds/translator/data_record_definitions/__init__.py
uds/translator/data_record_definitions/conditional.py
uds/translator/data_record_definitions/did.py
uds/translator/data_record_definitions/dtc.py
uds/translator/data_record_definitions/formula.py
uds/translator/data_record_definitions/other.py
py_uds-3.1.1.dist-info/METADATA
py_uds-3.1.1.dist-info/WHEEL
py_uds-3.1.1.dist-info/top_level.txt
py_uds-3.1.1.dist-info/RECORD
