Metadata-Version: 2.4
Name: py-uds
Version: 3.1.1
Summary: UDS (Unified Diagnostic Services) protocol handler.
Author-email: Maciej Dąbrowski <maciej.dabrowski@software-quality.pl>, UDS Package Development <uds-package-development@googlegroups.com>
Maintainer-email: Maciej Dąbrowski <maciej.dabrowski@software-quality.pl>, UDS Package Development <uds-package-development@googlegroups.com>
License-Expression: MIT
Project-URL: Homepage, https://github.com/mdabrowski1990/uds
Project-URL: User Documentation, https://uds.readthedocs.io
Project-URL: Repository, https://github.com/mdabrowski1990/uds
Project-URL: Issues Tracking System, https://github.com/mdabrowski1990/uds/issues
Project-URL: Releases and Changelogs, https://github.com/mdabrowski1990/uds/releases
Project-URL: Security Policy, https://github.com/mdabrowski1990/uds/security/policy
Project-URL: PyPI, https://pypi.org/project/py-uds/
Project-URL: Wiki, https://github.com/mdabrowski1990/uds/wiki
Project-URL: Code Download, https://github.com/mdabrowski1990/uds/archive/refs/heads/main.zip
Keywords: uds,unified-diagnostic-services,automotive,on-board-diagnostic,obd,obd2,vehicle-diagnostic,iso14229,iso-14229,iso15765,iso-15765
Classifier: Development Status :: 5 - Production/Stable
Classifier: Intended Audience :: Developers
Classifier: Intended Audience :: Education
Classifier: Intended Audience :: Information Technology
Classifier: Intended Audience :: Telecommunications Industry
Classifier: Natural Language :: English
Classifier: Operating System :: OS Independent
Classifier: Programming Language :: Python
Classifier: Programming Language :: Python :: 3
Classifier: Programming Language :: Python :: 3 :: Only
Classifier: Programming Language :: Python :: 3.10
Classifier: Programming Language :: Python :: 3.11
Classifier: Programming Language :: Python :: 3.12
Classifier: Programming Language :: Python :: 3.13
Classifier: Programming Language :: Python :: 3.14
Classifier: Topic :: Scientific/Engineering :: Interface Engine/Protocol Translator
Classifier: Topic :: Software Development :: Embedded Systems
Classifier: Topic :: System :: Monitoring
Classifier: Topic :: System :: Networking
Requires-Python: >=3.10
License-File: LICENSE
Requires-Dist: aenum>=3.0.0
Requires-Dist: python-can==4.*
Provides-Extra: test
Requires-Dist: mock==5.*; extra == "test"
Requires-Dist: pytest==8.*; extra == "test"
Requires-Dist: pytest-cov; extra == "test"
Requires-Dist: pytest-asyncio; extra == "test"
Provides-Extra: static-code-analysis
Requires-Dist: prospector==1.17.1; extra == "static-code-analysis"
Requires-Dist: mypy==1.16.1; extra == "static-code-analysis"
Requires-Dist: vulture==2.14; extra == "static-code-analysis"
Requires-Dist: bandit==1.8.5; extra == "static-code-analysis"
Requires-Dist: pyroma==5.0; extra == "static-code-analysis"
Provides-Extra: dependency-scan
Requires-Dist: pip-audit==2.9.0; extra == "dependency-scan"
Provides-Extra: sorting-imports
Requires-Dist: isort==6.0.1; extra == "sorting-imports"
Provides-Extra: docs
Requires-Dist: sphinx; extra == "docs"
Requires-Dist: sphinx-autoapi; extra == "docs"
Requires-Dist: sphinx-rtd-theme; extra == "docs"
Requires-Dist: tomli; extra == "docs"
Provides-Extra: docs-checks
Requires-Dist: doc8==1.1.1; extra == "docs-checks"
Dynamic: license-file
